lumigo_wrapper/__init__.py
lumigo_wrapper/lumigo_utils.py
lumigo_wrapper/wrapper.py
lumigo_wrapper/libs/__init__.py
lumigo_wrapper/libs/general_utils.py
lumigo_wrapper/libs/json_utils.py
lumigo_wrapper/parsers/__init__.py
lumigo_wrapper/parsers/botocore_parser.py
lumigo_wrapper/parsers/fastapi_parser.py
lumigo_wrapper/parsers/http_parser.py
lumigo_wrapper/utils/__init__.py
lumigo_wrapper/utils/aws_utils.py
lumigo_python_wrapper-0.3.14.dist-info/LICENSE
lumigo_python_wrapper-0.3.14.dist-info/METADATA
lumigo_python_wrapper-0.3.14.dist-info/WHEEL
lumigo_python_wrapper-0.3.14.dist-info/top_level.txt
lumigo_python_wrapper-0.3.14.dist-info/RECORD
