Metadata-Version: 2.1
Name: lumigo-python-wrapper
Version: 0.3.14
Summary: Lumigo wrapper to trace distributed architecture
Home-page: https://github.com/lumigo-io/lumigo-python-wrapper.git
Author: Lumigo LTD (https://lumigo.io)
Author-email: support@lumigo.io
License: Apache License 2.0
Platform: UNKNOWN
Classifier: Programming Language :: Python :: 3
Classifier: Operating System :: OS Independent
Requires-Dist: opentelemetry-api (==1.9.1)
Requires-Dist: opentelemetry-exporter-otlp (==1.9.1)
Requires-Dist: opentelemetry-proto (==1.9.1)
Requires-Dist: opentelemetry-exporter-zipkin (==1.10.0)
Requires-Dist: opentelemetry-exporter-zipkin-json (==1.10.0)
Requires-Dist: opentelemetry-exporter-zipkin-proto-http (==1.10.0)
Requires-Dist: opentelemetry-sdk (==1.9.1)
Requires-Dist: opentelemetry-instrumentation (==0.28b1)
Requires-Dist: opentelemetry-instrumentation-boto (==0.28b1)
Requires-Dist: opentelemetry-instrumentation-botocore (==0.28b1)
Requires-Dist: opentelemetry-instrumentation-flask (==0.28b1)
Requires-Dist: opentelemetry-instrumentation-requests (==0.28b1)
Requires-Dist: opentelemetry-instrumentation-wsgi (==0.28b1)
Requires-Dist: opentelemetry-instrumentation-fastapi (==0.28b1)
Requires-Dist: opentelemetry-semantic-conventions (==0.28b1)
Requires-Dist: flask (==1.1.2)
Requires-Dist: boto3 (==1.17.22)
Requires-Dist: boto (==2.49.0)
Requires-Dist: botocore (==1.20.112)
Requires-Dist: fastapi (==0.70.1)
Requires-Dist: requests (==2.27.1)
Requires-Dist: arnparse (==0.0.2)
Requires-Dist: click (==8.0.3)
Requires-Dist: importlib-metadata (==4.8.2)
Requires-Dist: itsdangerous (==2.0.1)
Requires-Dist: Jinja2 (==3.0.3)
Requires-Dist: MarkupSafe (==2.0.1)
Requires-Dist: typing-extensions (==4.0.1)
Requires-Dist: Werkzeug (==2.0.2)
Requires-Dist: zipp (==3.8.0)
